dicom2tar/DicomSorter.py
dicom2tar/__init__.py
dicom2tar/clinical_helpers.py
dicom2tar/main.py
dicom2tar/main.py.667140b7cbc33afff7460486f9d42bae.py
dicom2tar/sort_rules.py
dicom2tar-0.2.2.dist-info/LICENSE
dicom2tar-0.2.2.dist-info/METADATA
dicom2tar-0.2.2.dist-info/WHEEL
dicom2tar-0.2.2.dist-info/entry_points.txt
dicom2tar-0.2.2.dist-info/top_level.txt
dicom2tar-0.2.2.dist-info/RECORD
