Metadata-Version: 2.1
Name: dicom2tar
Version: 0.2.2
Summary: sort or tar CFMM' data with DicomSorter
Home-page: https://github.com/khanlab/dicom2tar
Author: YingLi Lu,Ali Khan
Author-email: alik.khanlab@gmail.com,yinglilu@gmail.com
License: GNU General Public License v3.0
Platform: UNKNOWN
Requires-Dist: pydicom (==1.1.0)
Requires-Dist: extractCMRRPhysio
Requires-Dist: DicomRaw
Requires-Dist: dcmstack (==0.7.0)
Requires-Dist: pandas (==0.24.1)
